<annotation>
	<folder>sumary</folder>
	<filename>airline_0015.jpg</filename>
	<path>/home/satou/Desktop/image/sumary/airline_0015.jpg</path>
	<source>
		<database>Unknown</database>
	</source>
	<size>
		<width>900</width>
		<height>600</height>
		<depth>3</depth>
	</size>
	<segmented>0</segmented>
	<object>
		<name>airlineText</name>
		<pose>Unspecified</pose>
		<truncated>0</truncated>
		<difficult>0</difficult>
		<bndbox>
			<xmin>470</xmin>
			<ymin>288</ymin>
			<xmax>525</xmax>
			<ymax>336</ymax>
		</bndbox>
	</object>
	<object>
		<name>airlineLogo</name>
		<pose>Unspecified</pose>
		<truncated>0</truncated>
		<difficult>0</difficult>
		<bndbox>
			<xmin>523</xmin>
			<ymin>325</ymin>
			<xmax>537</xmax>
			<ymax>344</ymax>
		</bndbox>
	</object>
</annotation>
